snowmicropyn/__init__.py
snowmicropyn/derivatives.py
snowmicropyn/detection.py
snowmicropyn/githash
snowmicropyn/loewe2012.py
snowmicropyn/match.py
snowmicropyn/pnt.py
snowmicropyn/profile.py
snowmicropyn/tools.py
snowmicropyn/windowing.py
snowmicropyn/ai/__init__.py
snowmicropyn/ai/grain_classifier.py
snowmicropyn/ai/trained_model_rhossa.dat
snowmicropyn/parameterizations/__init__.py
snowmicropyn/parameterizations/calonne_richter2020.py
snowmicropyn/parameterizations/king2020.py
snowmicropyn/parameterizations/proksch2015.py
snowmicropyn/pyngui/__init__.py
snowmicropyn/pyngui/about.html
snowmicropyn/pyngui/app.py
snowmicropyn/pyngui/document.py
snowmicropyn/pyngui/export_window.py
snowmicropyn/pyngui/export_window_niviz.py
snowmicropyn/pyngui/globals.py
snowmicropyn/pyngui/icons.py
snowmicropyn/pyngui/kml.py
snowmicropyn/pyngui/log_window.py
snowmicropyn/pyngui/main_window.py
snowmicropyn/pyngui/plot_canvas.py
snowmicropyn/pyngui/preferences.py
snowmicropyn/pyngui/sidebar.py
snowmicropyn/pyngui/superpos_canvas.py
snowmicropyn/serialize/__init__.py
snowmicropyn/serialize/caaml.py
snowmicropyn-1.2.1.dist-info/LICENSE.txt
snowmicropyn-1.2.1.dist-info/METADATA
snowmicropyn-1.2.1.dist-info/WHEEL
snowmicropyn-1.2.1.dist-info/entry_points.txt
snowmicropyn-1.2.1.dist-info/top_level.txt
snowmicropyn-1.2.1.dist-info/RECORD
