Metadata-Version: 2.1
Name: snowmicropyn
Version: 1.2.1
Summary: A Python package to read, export and post process data (*.pnt files) recorded by SnowMicroPen, a snow penetration probe for scientific applications developed at SLF.
Home-page: https://github.com/slf-dot-ch/snowmicropyn
Author: WSL Institute for Snow and Avalanche Research SLF
Author-email: snowmicropen@slf.ch
License: GPL
Keywords: SLF,SnowMicroPen,Snow Micro Pen,SMP,Snow,Science,Research
Platform: UNKNOWN
Classifier: Programming Language :: Python
Classifier: Programming Language :: Python :: 3
Classifier: Development Status :: 5 - Production/Stable
Classifier: Environment :: Other Environment
Classifier: Intended Audience :: Science/Research
Classifier: License :: OSI Approved :: GNU General Public License (GPL)
Classifier: Operating System :: OS Independent
Classifier: Topic :: Software Development :: Libraries :: Python Modules
Classifier: Topic :: Scientific/Engineering :: Atmospheric Science
Requires-Python: >=3.8
License-File: LICENSE.txt
Requires-Dist: PyQt5
Requires-Dist: matplotlib (>=2)
Requires-Dist: numpy
Requires-Dist: pandas (>=0.22)
Requires-Dist: pytz
Requires-Dist: scikit-learn
Requires-Dist: scipy (>=1)
